<Building>
    <name>Elf Settlement</name>

    <description>After Santa's death, housing market literally went nuts. Now we have to improvise shelters for our elves in metropolitan areas.</description>

    <score>0</score>
    <picture>ElfSettlement</picture>

    <income>
        <ResourceCount>
            <name>Elves</name>
            <value>2</value>
        </ResourceCount>

        <ResourceCount>
            <name>Humans</name>
            <value>0</value>
        </ResourceCount>
        
        <ResourceCount>
            <name>Gifts</name>
            <value>0</value>
        </ResourceCount>
        
        <ResourceCount>
            <name>Metals</name>
            <value>0</value>
        </ResourceCount>
        
        <ResourceCount>
            <name>Materials</name>
            <value>0</value>
        </ResourceCount>
    </income>

    <costs>
        <ResourceCount>
            <name>Elves</name>
            <value>5</value>
        </ResourceCount>

        <ResourceCount>
            <name>Humans</name>
            <value>0</value>
        </ResourceCount>
        
        <ResourceCount>
            <name>Gifts</name>
            <value>0</value>
        </ResourceCount>
        
        <ResourceCount>
            <name>Metals</name>
            <value>0</value>
        </ResourceCount>
        
        <ResourceCount>
            <name>Materials</name>
            <value>10</value>
        </ResourceCount>
    </costs>

</Building>